Metadata-Version: 2.4
Name: tabicl-survival
Version: 0.1.0
Summary: TabICL-Survival: A Tabular Foundation Model for Survival In-Context Learning
Project-URL: Documentation, https://github.com/taltstidl/tabicl-survival#readme
Project-URL: Issues, https://github.com/taltstidl/tabicl-survival/issues
Project-URL: Source, https://github.com/taltstidl/tabicl-survival
Author: Jingang Qu, David Holzmüller, Marine Le Morvan, Gaël Varoquaux, Thomas Altstidl
License: BSD 3-Clause License
License-File: LICENSE
Keywords: TabICL,foundation model,in-context learning,survival analysis,tabular data
Classifier: Development Status :: 4 - Beta
Classifier: Intended Audience :: Developers
Classifier: Intended Audience :: Science/Research
Classifier: Programming Language :: Python
Classifier: Programming Language :: Python :: 3
Classifier: Programming Language :: Python :: 3.9
Classifier: Programming Language :: Python :: 3.10
Classifier: Programming Language :: Python :: 3.11
Classifier: Programming Language :: Python :: 3.12
Classifier: Topic :: Scientific/Engineering
Requires-Python: <3.13,>=3.9
Requires-Dist: einops>=0.7
Requires-Dist: huggingface-hub
Requires-Dist: joblib
Requires-Dist: numpy
Requires-Dist: psutil
Requires-Dist: scikit-learn<1.7,>=1.3.0
Requires-Dist: scikit-survival
Requires-Dist: scipy
Requires-Dist: torch<3,>=2.2
Requires-Dist: tqdm>=4.64.0
Requires-Dist: transformers
Requires-Dist: wandb
Requires-Dist: xgboost
